{
    "puzzle": {
        "id": 29,
        "title": "WordGriddle #29",
        "locked": false,
        "difficulty": 2,
        "author": 2,
        "size": 4,
        "origin": 29,
        "letters": "CUREKRBLLDUBECOM",
        "keyWords": [
            [
                "blur",
                "[6][7][10][5]"
            ],
            [
                "bode",
                "[11][14][9][12]"
            ],
            [
                "buck",
                "[6][1][0][4]"
            ],
            [
                "bulb",
                "[6][10][7][11]"
            ],
            [
                "burr",
                "[11][10][5][2]"
            ],
            [
                "code",
                "[13][14][9][12]"
            ],
            [
                "comb",
                "[13][14][15][11]"
            ],
            [
                "cube",
                "[0][1][6][3]"
            ],
            [
                "curb",
                "[13][10][5][6]"
            ],
            [
                "curd",
                "[13][10][5][9]"
            ],
            [
                "cure",
                "[0][1][2][3]"
            ],
            [
                "curl",
                "[13][10][5][8]"
            ],
            [
                "dour",
                "[9][14][10][5]"
            ],
            [
                "drum",
                "[9][5][10][15]"
            ],
            [
                "dumb",
                "[9][10][15][11]"
            ],
            [
                "lube",
                "[7][10][6][3]"
            ],
            [
                "ludo",
                "[7][10][9][14]"
            ],
            [
                "lurk",
                "[7][10][5][4]"
            ],
            [
                "mode",
                "[15][14][9][12]"
            ],
            [
                "mule",
                "[15][10][7][3]"
            ],
            [
                "rude",
                "[5][10][9][12]"
            ],
            [
                "rule",
                "[5][10][7][3]"
            ],
            [
                "crude",
                "[0][5][10][9][12]"
            ],
            [
                "crumb",
                "[0][5][10][15][11]"
            ],
            [
                "elude",
                "[3][7][10][9][12]"
            ],
            [
                "model",
                "[15][14][9][12][8]"
            ],
            [
                "ruler",
                "[5][10][7][3][2]"
            ],
            [
                "buckle",
                "[6][1][0][4][8][12]"
            ],
            [
                "bumble",
                "[6][10][15][11][7][3]"
            ],
            [
                "cobble",
                "[13][14][11][6][7][3]"
            ],
            [
                "curdle",
                "[13][10][5][9][8][12]"
            ],
            [
                "curled",
                "[0][1][5][8][12][9]"
            ],
            [
                "double",
                "[9][14][10][11][7][3]"
            ],
            [
                "module",
                "[15][14][9][10][7][3]"
            ],
            [
                "rubber",
                "[5][10][11][6][3][2]"
            ],
            [
                "rubble",
                "[5][1][6][11][7][3]"
            ],
            [
                "rumble",
                "[5][10][15][11][7][3]"
            ],
            [
                "buckled",
                "[6][1][0][4][8][12][9]"
            ],
            [
                "cobbler",
                "[13][14][11][6][7][3][2]"
            ],
            [
                "crumble",
                "[0][5][10][15][11][7][3]"
            ]
        ],
        "extraWords": [
            [
                "bleb",
                "[11][7][3][6]"
            ],
            [
                "blub",
                "[11][7][10][6]"
            ],
            [
                "bubo",
                "[6][10][11][14]"
            ],
            [
                "bubu",
                "[11][10][6][1]"
            ],
            [
                "budo",
                "[6][10][9][14]"
            ],
            [
                "burb",
                "[11][10][5][6]"
            ],
            [
                "burd",
                "[6][1][5][9]"
            ],
            [
                "burk",
                "[6][10][5][4]"
            ],
            [
                "burl",
                "[6][10][5][8]"
            ],
            [
                "cobb",
                "[13][14][11][6]"
            ],
            [
                "cour",
                "[13][14][10][5]"
            ],
            [
                "crud",
                "[0][5][10][9]"
            ],
            [
                "curr",
                "[13][10][5][2]"
            ],
            [
                "deco",
                "[9][12][13][14]"
            ],
            [
                "douc",
                "[9][14][10][13]"
            ],
            [
                "doum",
                "[9][14][10][15]"
            ],
            [
                "drub",
                "[9][5][10][6]"
            ],
            [
                "duce",
                "[9][10][13][12]"
            ],
            [
                "dule",
                "[9][10][7][3]"
            ],
            [
                "durr",
                "[9][10][5][2]"
            ],
            [
                "ecod",
                "[12][13][14][9]"
            ],
            [
                "kuru",
                "[4][1][5][10]"
            ],
            [
                "luce",
                "[7][10][13][12]"
            ],
            [
                "lude",
                "[7][10][9][12]"
            ],
            [
                "murk",
                "[15][10][5][4]"
            ],
            [
                "murl",
                "[15][10][5][8]"
            ],
            [
                "murr",
                "[15][10][5][2]"
            ],
            [
                "ombu",
                "[14][15][11][10]"
            ],
            [
                "rube",
                "[5][10][6][3]"
            ],
            [
                "ruck",
                "[2][1][0][4]"
            ],
            [
                "ruru",
                "[2][1][5][10]"
            ],
            [
                "umbo",
                "[10][15][11][14]"
            ],
            [
                "urde",
                "[10][5][9][12]"
            ],
            [
                "blude",
                "[11][7][10][9][12]"
            ],
            [
                "blurb",
                "[11][7][10][5][6]"
            ],
            [
                "bodle",
                "[11][14][9][8][12]"
            ],
            [
                "boule",
                "[11][14][10][7][3]"
            ],
            [
                "bourd",
                "[11][14][10][5][9]"
            ],
            [
                "brule",
                "[6][5][10][7][3]"
            ],
            [
                "bumbo",
                "[6][10][15][11][14]"
            ],
            [
                "coble",
                "[13][14][11][7][3]"
            ],
            [
                "coude",
                "[13][14][10][9][12]"
            ],
            [
                "courb",
                "[13][14][10][5][6]"
            ],
            [
                "courd",
                "[13][14][10][5][9]"
            ],
            [
                "crudo",
                "[0][5][10][9][14]"
            ],
            [
                "cuber",
                "[13][10][6][3][2]"
            ],
            [
                "douce",
                "[9][14][10][13][12]"
            ],
            [
                "dubbo",
                "[9][10][6][11][14]"
            ],
            [
                "dumbo",
                "[9][10][15][11][14]"
            ],
            [
                "kurre",
                "[4][1][5][2][3]"
            ],
            [
                "ledum",
                "[8][12][9][10][15]"
            ],
            [
                "moble",
                "[15][14][11][7][3]"
            ],
            [
                "murre",
                "[15][10][5][2][3]"
            ],
            [
                "rubel",
                "[5][10][6][3][7]"
            ],
            [
                "ruble",
                "[5][10][6][7][3]"
            ],
            [
                "rumbo",
                "[5][10][15][11][14]"
            ],
            [
                "umble",
                "[10][15][11][7][3]"
            ],
            [
                "boucle",
                "[11][14][10][13][8][12]"
            ],
            [
                "burble",
                "[11][10][5][6][7][3]"
            ],
            [
                "burled",
                "[6][1][5][8][12][9]"
            ],
            [
                "burrel",
                "[11][10][5][2][3][7]"
            ],
            [
                "cobber",
                "[13][14][11][6][3][2]"
            ],
            [
                "comble",
                "[13][14][15][11][7][3]"
            ],
            [
                "curber",
                "[13][10][5][6][3][2]"
            ],
            [
                "curule",
                "[0][1][5][10][7][3]"
            ],
            [
                "dobber",
                "[9][14][11][6][3][2]"
            ],
            [
                "dubber",
                "[9][10][11][6][3][2]"
            ],
            [
                "lubber",
                "[7][10][11][6][3][2]"
            ],
            [
                "mobber",
                "[15][14][11][6][3][2]"
            ],
            [
                "mobble",
                "[15][14][11][6][7][3]"
            ],
            [
                "murled",
                "[15][10][5][8][12][9]"
            ],
            [
                "ruckle",
                "[2][1][0][4][8][12]"
            ],
            [
                "bruckle",
                "[6][5][1][0][4][8][12]"
            ],
            [
                "bubukle",
                "[11][10][6][1][4][8][12]"
            ],
            [
                "bumbler",
                "[6][10][15][11][7][3][2]"
            ],
            [
                "burbler",
                "[11][10][5][6][7][3][2]"
            ],
            [
                "doubler",
                "[9][14][10][11][7][3][2]"
            ],
            [
                "drubber",
                "[9][5][10][11][6][3][2]"
            ],
            [
                "drumble",
                "[9][5][10][15][11][7][3]"
            ],
            [
                "ruckled",
                "[2][1][0][4][8][12][9]"
            ],
            [
                "rumbler",
                "[5][10][15][11][7][3][2]"
            ]
        ]
    }
}