{
    "puzzle": {
        "id": 7,
        "title": "WordGriddle #7",
        "locked": false,
        "author": 1,
        "size": 4,
        "origin": 7,
        "letters": "WEGSINSRLERADEGN",
        "keyWords": [
            [
                "aged",
                "[11][14][13][12]"
            ],
            [
                "agee",
                "[11][14][13][9]"
            ],
            [
                "ager",
                "[11][14][9][10]"
            ],
            [
                "ages",
                "[11][14][9][6]"
            ],
            [
                "deer",
                "[12][13][9][10]"
            ],
            [
                "deli",
                "[12][13][8][4]"
            ],
            [
                "dens",
                "[12][9][5][6]"
            ],
            [
                "eras",
                "[13][10][11][6]"
            ],
            [
                "errs",
                "[9][10][7][6]"
            ],
            [
                "gene",
                "[2][1][5][9]"
            ],
            [
                "gran",
                "[14][10][11][15]"
            ],
            [
                "leer",
                "[8][9][13][10]"
            ],
            [
                "lens",
                "[8][9][5][6]"
            ],
            [
                "less",
                "[8][9][6][3]"
            ],
            [
                "lied",
                "[8][4][9][12]"
            ],
            [
                "lien",
                "[8][4][1][5]"
            ],
            [
                "lies",
                "[8][4][9][6]"
            ],
            [
                "line",
                "[8][4][5][9]"
            ],
            [
                "need",
                "[5][9][13][12]"
            ],
            [
                "rage",
                "[7][11][14][9]"
            ],
            [
                "rang",
                "[7][11][15][14]"
            ],
            [
                "rare",
                "[7][11][10][13]"
            ],
            [
                "reed",
                "[10][13][9][12]"
            ],
            [
                "reel",
                "[10][13][9][8]"
            ],
            [
                "rein",
                "[10][9][4][5]"
            ],
            [
                "sage",
                "[6][11][14][13]"
            ],
            [
                "sang",
                "[6][11][15][14]"
            ],
            [
                "seed",
                "[6][9][13][12]"
            ],
            [
                "seer",
                "[6][9][13][10]"
            ],
            [
                "sewn",
                "[6][1][0][5]"
            ],
            [
                "wild",
                "[0][4][8][12]"
            ],
            [
                "wile",
                "[0][4][8][9]"
            ],
            [
                "wine",
                "[0][4][5][1]"
            ],
            [
                "wing",
                "[0][4][5][2]"
            ],
            [
                "wins",
                "[0][4][5][6]"
            ],
            [
                "agree",
                "[11][14][10][9][13]"
            ],
            [
                "angel",
                "[11][15][14][13][8]"
            ],
            [
                "anger",
                "[11][15][14][9][10]"
            ],
            [
                "dense",
                "[12][9][5][6][1]"
            ],
            [
                "elder",
                "[9][8][12][13][10]"
            ],
            [
                "erase",
                "[13][10][11][6][9]"
            ],
            [
                "geese",
                "[14][13][9][6][1]"
            ],
            [
                "genes",
                "[2][1][5][9][6]"
            ],
            [
                "genie",
                "[14][9][5][4][1]"
            ],
            [
                "genre",
                "[2][1][5][10][13]"
            ],
            [
                "grass",
                "[2][7][11][6][3]"
            ],
            [
                "greed",
                "[14][10][9][13][12]"
            ],
            [
                "green",
                "[14][10][13][9][5]"
            ],
            [
                "leers",
                "[8][13][9][10][6]"
            ],
            [
                "lined",
                "[8][4][5][9][12]"
            ],
            [
                "liner",
                "[8][4][5][9][10]"
            ],
            [
                "lines",
                "[8][4][5][9][6]"
            ],
            [
                "raged",
                "[10][11][14][9][12]"
            ],
            [
                "rages",
                "[10][11][14][9][6]"
            ],
            [
                "range",
                "[7][11][15][14][13]"
            ],
            [
                "reins",
                "[10][9][4][5][6]"
            ],
            [
                "renew",
                "[10][9][5][1][0]"
            ],
            [
                "sneer",
                "[6][5][9][13][10]"
            ],
            [
                "wield",
                "[0][4][9][8][12]"
            ],
            [
                "wiles",
                "[0][4][8][9][6]"
            ],
            [
                "wined",
                "[0][4][5][9][12]"
            ],
            [
                "wines",
                "[0][4][5][9][6]"
            ],
            [
                "wings",
                "[0][4][5][2][6]"
            ],
            [
                "ageing",
                "[11][14][9][4][5][2]"
            ],
            [
                "agreed",
                "[11][14][10][9][13][12]"
            ],
            [
                "agrees",
                "[11][14][10][13][9][6]"
            ],
            [
                "angers",
                "[11][15][14][9][10][6]"
            ],
            [
                "denies",
                "[12][9][5][4][1][6]"
            ],
            [
                "egress",
                "[13][14][10][9][6][3]"
            ],
            [
                "elders",
                "[9][8][12][13][10][6]"
            ],
            [
                "enrage",
                "[9][5][10][11][14][13]"
            ],
            [
                "erased",
                "[13][10][11][6][9][12]"
            ],
            [
                "genies",
                "[2][1][5][4][9][6]"
            ],
            [
                "genres",
                "[2][1][5][10][9][6]"
            ],
            [
                "grange",
                "[2][7][11][15][14][9]"
            ],
            [
                "greens",
                "[14][10][13][9][5][6]"
            ],
            [
                "liners",
                "[8][4][5][9][10][6]"
            ],
            [
                "ranged",
                "[7][11][15][14][13][12]"
            ],
            [
                "ranger",
                "[7][11][15][14][9][10]"
            ],
            [
                "ranges",
                "[7][11][15][14][9][6]"
            ],
            [
                "relied",
                "[10][13][8][4][9][12]"
            ],
            [
                "relies",
                "[10][13][8][4][9][6]"
            ],
            [
                "reline",
                "[10][13][8][4][5][1]"
            ],
            [
                "senile",
                "[6][9][5][4][8][13]"
            ],
            [
                "sewing",
                "[6][1][0][4][5][2]"
            ],
            [
                "wilder",
                "[0][4][8][12][13][10]"
            ],
            [
                "ageless",
                "[11][14][13][8][9][6][3]"
            ],
            [
                "angered",
                "[11][15][14][13][10][9][12]"
            ],
            [
                "derange",
                "[12][13][10][11][15][14][9]"
            ],
            [
                "enraged",
                "[9][5][10][11][14][13][12]"
            ],
            [
                "enrages",
                "[1][5][10][11][14][9][6]"
            ],
            [
                "granges",
                "[2][7][11][15][14][9][6]"
            ],
            [
                "linseed",
                "[8][4][5][6][9][13][12]"
            ],
            [
                "rangers",
                "[7][11][15][14][9][10][6]"
            ],
            [
                "reeling",
                "[10][9][13][8][4][5][2]"
            ],
            [
                "winless",
                "[0][4][5][8][9][6][3]"
            ],
            [
                "agreeing",
                "[11][14][10][13][9][4][5][2]"
            ],
            [
                "rareness",
                "[7][11][10][9][5][1][6][3]"
            ],
            [
                "seedling",
                "[6][9][13][12][8][4][5][2]"
            ],
            [
                "seedlings",
                "[6][9][13][12][8][4][5][2][3]"
            ],
            [
                "wilderness",
                "[0][4][8][12][13][10][5][9][6][3]"
            ]
        ],
        "extraWords": [
            [
                "areg",
                "[11][10][9][14]"
            ],
            [
                "ares",
                "[11][10][9][6]"
            ],
            [
                "dees",
                "[12][13][9][6]"
            ],
            [
                "deil",
                "[12][9][4][8]"
            ],
            [
                "dele",
                "[12][9][8][13]"
            ],
            [
                "dene",
                "[12][9][5][1]"
            ],
            [
                "deni",
                "[12][9][5][4]"
            ],
            [
                "dere",
                "[12][13][10][9]"
            ],
            [
                "eger",
                "[9][14][13][10]"
            ],
            [
                "engs",
                "[9][5][2][6]"
            ],
            [
                "erne",
                "[9][10][5][1]"
            ],
            [
                "erns",
                "[9][10][5][6]"
            ],
            [
                "esne",
                "[9][6][5][1]"
            ],
            [
                "gars",
                "[14][11][7][6]"
            ],
            [
                "geed",
                "[14][9][13][12]"
            ],
            [
                "gees",
                "[14][13][9][6]"
            ],
            [
                "geld",
                "[14][9][8][12]"
            ],
            [
                "gens",
                "[2][1][5][6]"
            ],
            [
                "gnar",
                "[14][15][11][10]"
            ],
            [
                "gree",
                "[14][10][13][9]"
            ],
            [
                "lede",
                "[8][13][12][9]"
            ],
            [
                "lees",
                "[8][13][9][6]"
            ],
            [
                "lier",
                "[8][4][9][10]"
            ],
            [
                "ling",
                "[8][4][5][2]"
            ],
            [
                "lins",
                "[8][4][5][6]"
            ],
            [
                "nare",
                "[15][11][10][9]"
            ],
            [
                "negs",
                "[5][1][2][6]"
            ],
            [
                "ness",
                "[5][9][6][3]"
            ],
            [
                "rase",
                "[7][11][6][9]"
            ],
            [
                "rede",
                "[10][13][12][9]"
            ],
            [
                "rees",
                "[10][13][9][6]"
            ],
            [
                "seel",
                "[6][9][13][8]"
            ],
            [
                "segs",
                "[6][1][2][3]"
            ],
            [
                "sene",
                "[6][1][5][9]"
            ],
            [
                "sera",
                "[6][9][10][11]"
            ],
            [
                "sere",
                "[6][9][10][13]"
            ],
            [
                "sned",
                "[6][5][9][12]"
            ],
            [
                "wens",
                "[0][1][5][6]"
            ],
            [
                "agene",
                "[11][14][9][5][1]"
            ],
            [
                "agers",
                "[11][14][13][10][6]"
            ],
            [
                "arene",
                "[11][10][9][5][1]"
            ],
            [
                "deers",
                "[12][9][13][10][6]"
            ],
            [
                "degas",
                "[12][9][14][11][6]"
            ],
            [
                "deles",
                "[12][13][8][9][6]"
            ],
            [
                "denes",
                "[12][9][5][1][6]"
            ],
            [
                "egers",
                "[9][14][13][10][6]"
            ],
            [
                "ernes",
                "[13][10][5][9][6]"
            ],
            [
                "garni",
                "[14][11][10][5][4]"
            ],
            [
                "gnarr",
                "[14][15][11][7][10]"
            ],
            [
                "gnars",
                "[14][15][11][7][3]"
            ],
            [
                "grees",
                "[14][10][13][9][6]"
            ],
            [
                "ledes",
                "[8][13][12][9][6]"
            ],
            [
                "leger",
                "[8][13][14][9][10]"
            ],
            [
                "leges",
                "[8][13][14][9][6]"
            ],
            [
                "lenes",
                "[8][9][5][1][6]"
            ],
            [
                "lense",
                "[8][9][5][6][1]"
            ],
            [
                "liege",
                "[8][4][9][14][13]"
            ],
            [
                "liens",
                "[8][4][9][5][6]"
            ],
            [
                "liers",
                "[8][4][9][10][6]"
            ],
            [
                "lings",
                "[8][4][5][2][3]"
            ],
            [
                "nares",
                "[15][11][10][9][6]"
            ],
            [
                "newie",
                "[5][1][0][4][9]"
            ],
            [
                "ragee",
                "[10][11][14][13][9]"
            ],
            [
                "rager",
                "[7][11][14][9][10]"
            ],
            [
                "rared",
                "[7][11][10][13][12]"
            ],
            [
                "rares",
                "[7][11][10][9][6]"
            ],
            [
                "rased",
                "[7][11][6][9][12]"
            ],
            [
                "raser",
                "[7][11][6][9][10]"
            ],
            [
                "redes",
                "[10][13][12][9][6]"
            ],
            [
                "reges",
                "[10][13][14][9][6]"
            ],
            [
                "regna",
                "[10][9][14][15][11]"
            ],
            [
                "resew",
                "[10][9][6][1][0]"
            ],
            [
                "sager",
                "[6][11][14][9][10]"
            ],
            [
                "saree",
                "[6][11][10][13][9]"
            ],
            [
                "sarge",
                "[6][11][10][14][9]"
            ],
            [
                "seder",
                "[6][9][12][13][10]"
            ],
            [
                "segni",
                "[6][1][2][5][4]"
            ],
            [
                "seine",
                "[6][1][4][5][9]"
            ],
            [
                "sered",
                "[6][9][10][13][12]"
            ],
            [
                "serge",
                "[6][9][10][14][13]"
            ],
            [
                "wiled",
                "[0][4][8][13][12]"
            ],
            [
                "agenes",
                "[11][14][9][5][1][6]"
            ],
            [
                "arenes",
                "[11][10][9][5][1][6]"
            ],
            [
                "eeling",
                "[9][13][8][4][5][2]"
            ],
            [
                "garred",
                "[14][11][7][10][13][12]"
            ],
            [
                "geeing",
                "[14][13][9][4][5][2]"
            ],
            [
                "gelder",
                "[14][9][8][12][13][10]"
            ],
            [
                "genera",
                "[2][1][5][9][10][11]"
            ],
            [
                "gnarrs",
                "[14][15][11][10][7][3]"
            ],
            [
                "legers",
                "[8][9][14][13][10][6]"
            ],
            [
                "lieder",
                "[8][4][9][12][13][10]"
            ],
            [
                "lierne",
                "[8][4][9][10][5][1]"
            ],
            [
                "newies",
                "[5][1][0][4][9][6]"
            ],
            [
                "ragees",
                "[10][11][14][13][9][6]"
            ],
            [
                "ragers",
                "[7][11][14][9][10][6]"
            ],
            [
                "redleg",
                "[10][13][12][8][9][14]"
            ],
            [
                "resewn",
                "[10][9][6][1][0][5]"
            ],
            [
                "sanger",
                "[6][11][15][14][9][10]"
            ],
            [
                "sarnie",
                "[6][11][10][5][4][1]"
            ],
            [
                "seined",
                "[6][1][4][5][9][12]"
            ],
            [
                "seiner",
                "[6][1][4][5][9][10]"
            ],
            [
                "senega",
                "[6][1][5][9][14][11]"
            ],
            [
                "serged",
                "[6][9][10][14][13][12]"
            ],
            [
                "weiner",
                "[0][1][4][5][9][10]"
            ],
            [
                "wiener",
                "[0][4][1][5][9][10]"
            ],
            [
                "ageings",
                "[11][14][9][4][5][2][6]"
            ],
            [
                "angeled",
                "[11][15][14][13][8][9][12]"
            ],
            [
                "deleing",
                "[12][13][8][9][4][5][2]"
            ],
            [
                "eelings",
                "[9][13][8][4][5][2][6]"
            ],
            [
                "gelders",
                "[14][13][8][12][9][10][6]"
            ],
            [
                "gnarred",
                "[14][15][11][7][10][13][12]"
            ],
            [
                "granger",
                "[2][7][11][15][14][13][10]"
            ],
            [
                "greeing",
                "[14][10][13][9][4][5][2]"
            ],
            [
                "greenie",
                "[14][10][13][9][5][4][1]"
            ],
            [
                "liernes",
                "[8][4][9][10][5][1][6]"
            ],
            [
                "linsang",
                "[8][4][5][6][11][15][14]"
            ],
            [
                "redline",
                "[10][13][12][8][4][5][9]"
            ],
            [
                "relined",
                "[10][13][8][4][5][9][12]"
            ],
            [
                "relines",
                "[10][9][8][4][5][1][6]"
            ],
            [
                "seeling",
                "[6][9][13][8][4][5][2]"
            ],
            [
                "sewings",
                "[6][1][0][4][5][2][3]"
            ],
            [
                "weiners",
                "[0][1][4][5][9][10][6]"
            ],
            [
                "wielder",
                "[0][4][9][8][12][13][10]"
            ],
            [
                "wieners",
                "[0][4][1][5][9][10][6]"
            ],
            [
                "wilders",
                "[0][4][8][12][9][10][6]"
            ],
            [
                "angeling",
                "[11][15][14][13][8][4][5][2]"
            ],
            [
                "deranges",
                "[12][13][10][11][15][14][9][6]"
            ],
            [
                "grangers",
                "[2][7][11][15][14][9][10][6]"
            ],
            [
                "greenies",
                "[14][10][13][9][5][4][1][6]"
            ],
            [
                "redenies",
                "[10][13][12][9][5][4][1][6]"
            ],
            [
                "redlines",
                "[10][9][12][8][4][5][1][6]"
            ],
            [
                "reedling",
                "[10][13][9][12][8][4][5][2]"
            ],
            [
                "reelings",
                "[10][13][9][8][4][5][2][3]"
            ],
            [
                "resewing",
                "[10][9][6][1][0][4][5][2]"
            ],
            [
                "wielders",
                "[0][4][9][8][12][13][10][6]"
            ],
            [
                "reedlings",
                "[10][13][9][12][8][4][5][2][3]"
            ]
        ]
    }
}